defcli/__init__.py
defcli/defcli.py
defcli/tests/__init__.py
defcli/tests/test_misc.py
defcli/tests/test_readme.py
defcli-0.0.2.dist-info/METADATA
defcli-0.0.2.dist-info/WHEEL
defcli-0.0.2.dist-info/licenses/LICENSE
defcli-0.0.2.dist-info/RECORD
