Metadata-Version: 2.1
Name: defcli
Version: 0.0.2
Summary: def your CLIs
Project-URL: Homepage, https://gitlab.com/mggmuggins/defcli
Project-URL: Bug Tracker, https://gitlab.com/mggmuggins/defcli/issues
Author-email: Wesley Hershberger <mggmugginsmc@gmail.com>
License-File: LICENSE
Classifier: License :: OSI Approved :: MIT License
Classifier: Operating System :: OS Independent
Classifier: Programming Language :: Python :: 3
Requires-Python: >=3.10
